{"ssc": false, "version": "A20", "name": "50th Memorial Songs -futari no toki ~under the cherry blossoms~-", "title": "50th Memorial Songs -\u4e8c\u4eba\u306e\u6642 \uff5eunder the cherry blossoms\uff5e-", "titletranslit": "50th Memorial Songs -futari no toki ~under the cherry blossoms~-", "song_length": 121.5, "per_chart": false, "sp": {"beginner": 3, "easy": 7, "medium": 9, "hard": 12}, "dp": {"easy": 7, "medium": 9, "hard": 11}, "charts": [{"dominant_bpm": 160, "true_min": 160, "true_max": 160, "bpm_range": "160", "bpms": [{"st": 0.0, "ed": 121.5, "val": 160}], "stops": []}]}