{"ssc": false, "version": "A20", "name": "BUTTERFLY (20th Anniversary Mix)", "title": "BUTTERFLY (20th Anniversary Mix)", "titletranslit": "BUTTERFLY (20th Anniversary Mix)", "song_length": 121.714, "per_chart": false, "sp": {"beginner": 3, "easy": 6, "medium": 9, "hard": 12, "challenge": 16}, "dp": {"easy": 6, "medium": 10, "hard": 12, "challenge": 16}, "charts": [{"dominant_bpm": 140, "true_min": 140, "true_max": 140, "bpm_range": "140", "bpms": [{"st": 0.0, "ed": 121.714, "val": 140}], "stops": []}]}