{"ssc": false, "version": "A", "name": "First Time", "title": "First Time", "titletranslit": "First Time", "song_length": 100.072, "per_chart": false, "sp": {"beginner": 4, "easy": 7, "medium": 11, "hard": 15, "challenge": 18}, "dp": {"easy": 7, "medium": 11, "hard": 15, "challenge": 18}, "charts": [{"dominant_bpm": 140, "true_min": 70, "true_max": 560, "bpm_range": "140", "bpms": [{"st": 0.0, "ed": 48.858, "val": 140}, {"st": 48.858, "ed": 49.715, "val": 70}, {"st": 49.715, "ed": 62.572, "val": 140}, {"st": 62.572, "ed": 63.0, "val": 70}, {"st": 63.0, "ed": 69.857, "val": 140}, {"st": 69.857, "ed": 70.286, "val": 70}, {"st": 70.286, "ed": 76.5, "val": 140}, {"st": 76.5, "ed": 77.143, "val": 560}, {"st": 77.143, "ed": 79.929, "val": 140}, {"st": 79.929, "ed": 80.572, "val": 93}, {"st": 80.572, "ed": 83.572, "val": 140}, {"st": 83.572, "ed": 84.0, "val": 70}, {"st": 84.0, "ed": 100.072, "val": 140}], "stops": [{"st": 28.473, "dur": 0.643, "beats": [{"bpm": 140, "val": 1.5}]}, {"st": 41.143, "dur": 0.429, "beats": [{"bpm": 140, "val": 1.0}]}, {"st": 56.143, "dur": 0.214, "beats": [{"bpm": 140, "val": 0.5}]}]}]}