{"ssc": false, "version": "SuperNOVA", "name": "MAXIMIZER", "title": "MAXIMIZER", "titletranslit": "MAXIMIZER", "song_length": 95.054, "per_chart": false, "sp": {"beginner": 5, "easy": 6, "medium": 9, "hard": 12}, "dp": {"easy": 6, "medium": 9, "hard": 11}, "charts": [{"dominant_bpm": 190, "true_min": 190, "true_max": 190, "bpm_range": "190", "bpms": [{"st": 0.0, "ed": 95.054, "val": 190}], "stops": [{"st": 6.316, "dur": 0.632, "beats": [{"bpm": 190, "val": 2.0}]}, {"st": 27.158, "dur": 0.316, "beats": [{"bpm": 190, "val": 1.0}]}, {"st": 47.053, "dur": 0.632, "beats": [{"bpm": 190, "val": 2.0}]}]}]}