{"ssc": false, "version": "SuperNOVA2", "name": "STARS (Re-tuned by HAL) - DDR EDITION -", "title": "STARS\u2606\u2606\u2606 (Re-tuned by H\u039bL) - DDR EDITION -", "titletranslit": "STARS\u2606\u2606\u2606 (Re-tuned by H\u039bL) - DDR EDITION -", "song_length": 97.647, "per_chart": false, "sp": {"beginner": 3, "easy": 5, "medium": 10, "hard": 9}, "dp": {"easy": 6, "medium": 9, "hard": 10}, "charts": [{"dominant_bpm": 145, "true_min": 145, "true_max": 145, "bpm_range": "145", "bpms": [{"st": 0.0, "ed": 97.647, "val": 145}], "stops": []}]}